.gitignore
asyncmy/charset.pyx
asyncmy/auth.py
asyncmy/converters.cpython-313-darwin.so
asyncmy/cursors.c
asyncmy/cursors.pyx
asyncmy/protocol.pyx
asyncmy/version.py
asyncmy/errors.pyx
asyncmy/charset.cpython-313-darwin.so
asyncmy/connection.pyx
asyncmy/converters.pyx
asyncmy/protocol.cpython-313-darwin.so
asyncmy/pool.pyx
asyncmy/__init__.py
asyncmy/structs.py
asyncmy/connection.c
asyncmy/protocol.c
asyncmy/errors.cpython-313-darwin.so
asyncmy/converters.c
asyncmy/cursors.cpython-313-darwin.so
asyncmy/pool.c
asyncmy/pool.cpython-313-darwin.so
asyncmy/charset.c
asyncmy/contexts.py
asyncmy/connection.cpython-313-darwin.so
asyncmy/optionfile.py
asyncmy/charset.pxd
asyncmy/errors.c
asyncmy/constants/FLAG.py
asyncmy/constants/COMMAND.py
asyncmy/constants/CLIENT.py
asyncmy/constants/__init__.py
asyncmy/constants/ER.py
asyncmy/constants/CR.py
asyncmy/constants/SERVER_STATUS.py
asyncmy/constants/FIELD_TYPE.py
asyncmy/constants/COLUMN.py
asyncmy/replication/gtid.py
asyncmy/replication/events.py
asyncmy/replication/constants.py
asyncmy/replication/__init__.py
asyncmy/replication/row_events.py
asyncmy/replication/utils.py
asyncmy/replication/table.py
asyncmy/replication/errors.py
asyncmy/replication/bitmap.py
asyncmy/replication/binlogstream.py
asyncmy/replication/column.py
asyncmy/replication/packets.py
asyncmy2-0.2.20.dist-info/RECORD
asyncmy2-0.2.20.dist-info/WHEEL
asyncmy2-0.2.20.dist-info/entry_points.txt
asyncmy2-0.2.20.dist-info/METADATA
asyncmy2-0.2.20.dist-info/licenses/LICENSE
