Metadata-Version: 2.4
Name: asyncmy2
Version: 0.2.20
Summary: A fast asyncio MySQL driver
Keywords: driver,asyncio,mysql
Author-Email: vpmedia <andras@vpmedia.hu>, long2ice <long2ice@gmail.com>
License-Expression: Apache-2.0
Project-URL: documentation, https://github.com/vpmedia/asyncmy2
Project-URL: homepage, https://github.com/vpmedia/asyncmy2
Project-URL: repository, https://github.com/vpmedia/asyncmy2.git
Requires-Python: >=3.10
